{
  "generated_at": "2026-05-10T04:29:18.887306Z",
  "generated_at_kst": "2026-05-10 KST",
  "source": "VM Cloud SQLite read-only / npay_intent_log",
  "raw_click_ids_in_output": false,
  "results": [
    {
      "order_no": "202605109700078",
      "channel_order_no": "2026051018534650",
      "payment_amount": 117000,
      "order_time": "2026-05-10T01:32:29.000Z",
      "lookback_hours": 24,
      "candidate_count": 50,
      "exact_price_click_candidate_count": 0,
      "top_candidates": [
        {
          "intent_id": "b6ce2441-53ab-464c-b06e-b1a8455404ac",
          "captured_at": "2026-05-10T01:32:28.850Z",
          "received_at": "2026-05-10T01:32:29.152Z",
          "product_idx": "198",
          "product_price": 35000,
          "price_matches_order_amount": false,
          "client_id_present": true,
          "ga_session_id_present": true,
          "click_id_present": false,
          "click_id_hash_prefix": "",
          "match_status": "pending",
          "matched_order_no_present": false,
          "matched_amount_matches": false,
          "matched_payment_method": "",
          "match_confidence": null,
          "match_reason": ""
        },
        {
          "intent_id": "1797e3fc-9c3f-4210-a563-0aa7f9e06651",
          "captured_at": "2026-05-10T01:27:36.663Z",
          "received_at": "2026-05-10T01:27:36.969Z",
          "product_idx": "97",
          "product_price": 39000,
          "price_matches_order_amount": false,
          "client_id_present": true,
          "ga_session_id_present": true,
          "click_id_present": true,
          "click_id_hash_prefix": "a25a7c1b0111fad3",
          "match_status": "pending",
          "matched_order_no_present": false,
          "matched_amount_matches": false,
          "matched_payment_method": "",
          "match_confidence": null,
          "match_reason": ""
        },
        {
          "intent_id": "bd0e085f-3e9c-4114-ad05-e51f44cd8747",
          "captured_at": "2026-05-10T01:08:27.804Z",
          "received_at": "2026-05-10T01:08:29.193Z",
          "product_idx": "300",
          "product_price": 36000,
          "price_matches_order_amount": false,
          "client_id_present": true,
          "ga_session_id_present": true,
          "click_id_present": true,
          "click_id_hash_prefix": "7d45e22986a1b229",
          "match_status": "pending",
          "matched_order_no_present": false,
          "matched_amount_matches": false,
          "matched_payment_method": "",
          "match_confidence": null,
          "match_reason": ""
        },
        {
          "intent_id": "e2466c8f-81d5-462b-80d0-65fcbbffea07",
          "captured_at": "2026-05-10T00:11:05.173Z",
          "received_at": "2026-05-10T00:11:06.036Z",
          "product_idx": "317",
          "product_price": 59800,
          "price_matches_order_amount": false,
          "client_id_present": true,
          "ga_session_id_present": true,
          "click_id_present": true,
          "click_id_hash_prefix": "7636f77048d65511",
          "match_status": "pending",
          "matched_order_no_present": false,
          "matched_amount_matches": false,
          "matched_payment_method": "",
          "match_confidence": null,
          "match_reason": ""
        },
        {
          "intent_id": "cbe186bd-3100-433c-9e83-dcadc42126cd",
          "captured_at": "2026-05-09T23:41:17.905Z",
          "received_at": "2026-05-09T23:41:19.010Z",
          "product_idx": "317",
          "product_price": 59800,
          "price_matches_order_amount": false,
          "client_id_present": true,
          "ga_session_id_present": true,
          "click_id_present": true,
          "click_id_hash_prefix": "16dd5450371b3bb4",
          "match_status": "pending",
          "matched_order_no_present": false,
          "matched_amount_matches": false,
          "matched_payment_method": "",
          "match_confidence": null,
          "match_reason": ""
        },
        {
          "intent_id": "ec1de051-e4fb-41c9-8a9c-4d5b1c14b17e",
          "captured_at": "2026-05-09T23:22:36.509Z",
          "received_at": "2026-05-09T23:22:37.793Z",
          "product_idx": "173",
          "product_price": 36000,
          "price_matches_order_amount": false,
          "client_id_present": true,
          "ga_session_id_present": true,
          "click_id_present": false,
          "click_id_hash_prefix": "",
          "match_status": "pending",
          "matched_order_no_present": false,
          "matched_amount_matches": false,
          "matched_payment_method": "",
          "match_confidence": null,
          "match_reason": ""
        },
        {
          "intent_id": "1a1c7698-acd7-46df-a469-b95b75e4c7c7",
          "captured_at": "2026-05-09T22:38:40.419Z",
          "received_at": "2026-05-09T22:38:40.179Z",
          "product_idx": "198",
          "product_price": 35000,
          "price_matches_order_amount": false,
          "client_id_present": true,
          "ga_session_id_present": true,
          "click_id_present": true,
          "click_id_hash_prefix": "51b541e31be7e73a",
          "match_status": "pending",
          "matched_order_no_present": false,
          "matched_amount_matches": false,
          "matched_payment_method": "",
          "match_confidence": null,
          "match_reason": ""
        },
        {
          "intent_id": "9b6d57bf-7d3e-4ffc-8f98-7b3cbcb533b5",
          "captured_at": "2026-05-09T22:28:48.221Z",
          "received_at": "2026-05-09T22:28:48.460Z",
          "product_idx": "317",
          "product_price": 59800,
          "price_matches_order_amount": false,
          "client_id_present": true,
          "ga_session_id_present": true,
          "click_id_present": true,
          "click_id_hash_prefix": "278fc0a58a86bb27",
          "match_status": "pending",
          "matched_order_no_present": false,
          "matched_amount_matches": false,
          "matched_payment_method": "",
          "match_confidence": null,
          "match_reason": ""
        },
        {
          "intent_id": "77fdeaf4-fe74-4434-a785-3c5b26c6abed",
          "captured_at": "2026-05-09T22:21:55.083Z",
          "received_at": "2026-05-09T22:21:56.690Z",
          "product_idx": "300",
          "product_price": 36000,
          "price_matches_order_amount": false,
          "client_id_present": true,
          "ga_session_id_present": true,
          "click_id_present": true,
          "click_id_hash_prefix": "1af66527003686e9",
          "match_status": "pending",
          "matched_order_no_present": false,
          "matched_amount_matches": false,
          "matched_payment_method": "",
          "match_confidence": null,
          "match_reason": ""
        },
        {
          "intent_id": "c70a1e17-2c5b-4f9b-98bf-79fdf4a9ce7c",
          "captured_at": "2026-05-09T21:46:26.658Z",
          "received_at": "2026-05-09T21:46:26.974Z",
          "product_idx": "317",
          "product_price": 59800,
          "price_matches_order_amount": false,
          "client_id_present": true,
          "ga_session_id_present": true,
          "click_id_present": true,
          "click_id_hash_prefix": "50ae537f74eda14b",
          "match_status": "pending",
          "matched_order_no_present": false,
          "matched_amount_matches": false,
          "matched_payment_method": "",
          "match_confidence": null,
          "match_reason": ""
        }
      ],
      "verdict": "ambiguous_or_missing"
    },
    {
      "order_no": "202605104467942",
      "channel_order_no": "2026051018446030",
      "payment_amount": 39000,
      "order_time": "2026-05-10T01:27:37.000Z",
      "lookback_hours": 24,
      "candidate_count": 50,
      "exact_price_click_candidate_count": 8,
      "top_candidates": [
        {
          "intent_id": "1797e3fc-9c3f-4210-a563-0aa7f9e06651",
          "captured_at": "2026-05-10T01:27:36.663Z",
          "received_at": "2026-05-10T01:27:36.969Z",
          "product_idx": "97",
          "product_price": 39000,
          "price_matches_order_amount": true,
          "client_id_present": true,
          "ga_session_id_present": true,
          "click_id_present": true,
          "click_id_hash_prefix": "a25a7c1b0111fad3",
          "match_status": "pending",
          "matched_order_no_present": false,
          "matched_amount_matches": false,
          "matched_payment_method": "",
          "match_confidence": null,
          "match_reason": ""
        },
        {
          "intent_id": "bd0e085f-3e9c-4114-ad05-e51f44cd8747",
          "captured_at": "2026-05-10T01:08:27.804Z",
          "received_at": "2026-05-10T01:08:29.193Z",
          "product_idx": "300",
          "product_price": 36000,
          "price_matches_order_amount": false,
          "client_id_present": true,
          "ga_session_id_present": true,
          "click_id_present": true,
          "click_id_hash_prefix": "7d45e22986a1b229",
          "match_status": "pending",
          "matched_order_no_present": false,
          "matched_amount_matches": false,
          "matched_payment_method": "",
          "match_confidence": null,
          "match_reason": ""
        },
        {
          "intent_id": "e2466c8f-81d5-462b-80d0-65fcbbffea07",
          "captured_at": "2026-05-10T00:11:05.173Z",
          "received_at": "2026-05-10T00:11:06.036Z",
          "product_idx": "317",
          "product_price": 59800,
          "price_matches_order_amount": false,
          "client_id_present": true,
          "ga_session_id_present": true,
          "click_id_present": true,
          "click_id_hash_prefix": "7636f77048d65511",
          "match_status": "pending",
          "matched_order_no_present": false,
          "matched_amount_matches": false,
          "matched_payment_method": "",
          "match_confidence": null,
          "match_reason": ""
        },
        {
          "intent_id": "cbe186bd-3100-433c-9e83-dcadc42126cd",
          "captured_at": "2026-05-09T23:41:17.905Z",
          "received_at": "2026-05-09T23:41:19.010Z",
          "product_idx": "317",
          "product_price": 59800,
          "price_matches_order_amount": false,
          "client_id_present": true,
          "ga_session_id_present": true,
          "click_id_present": true,
          "click_id_hash_prefix": "16dd5450371b3bb4",
          "match_status": "pending",
          "matched_order_no_present": false,
          "matched_amount_matches": false,
          "matched_payment_method": "",
          "match_confidence": null,
          "match_reason": ""
        },
        {
          "intent_id": "ec1de051-e4fb-41c9-8a9c-4d5b1c14b17e",
          "captured_at": "2026-05-09T23:22:36.509Z",
          "received_at": "2026-05-09T23:22:37.793Z",
          "product_idx": "173",
          "product_price": 36000,
          "price_matches_order_amount": false,
          "client_id_present": true,
          "ga_session_id_present": true,
          "click_id_present": false,
          "click_id_hash_prefix": "",
          "match_status": "pending",
          "matched_order_no_present": false,
          "matched_amount_matches": false,
          "matched_payment_method": "",
          "match_confidence": null,
          "match_reason": ""
        },
        {
          "intent_id": "1a1c7698-acd7-46df-a469-b95b75e4c7c7",
          "captured_at": "2026-05-09T22:38:40.419Z",
          "received_at": "2026-05-09T22:38:40.179Z",
          "product_idx": "198",
          "product_price": 35000,
          "price_matches_order_amount": false,
          "client_id_present": true,
          "ga_session_id_present": true,
          "click_id_present": true,
          "click_id_hash_prefix": "51b541e31be7e73a",
          "match_status": "pending",
          "matched_order_no_present": false,
          "matched_amount_matches": false,
          "matched_payment_method": "",
          "match_confidence": null,
          "match_reason": ""
        },
        {
          "intent_id": "9b6d57bf-7d3e-4ffc-8f98-7b3cbcb533b5",
          "captured_at": "2026-05-09T22:28:48.221Z",
          "received_at": "2026-05-09T22:28:48.460Z",
          "product_idx": "317",
          "product_price": 59800,
          "price_matches_order_amount": false,
          "client_id_present": true,
          "ga_session_id_present": true,
          "click_id_present": true,
          "click_id_hash_prefix": "278fc0a58a86bb27",
          "match_status": "pending",
          "matched_order_no_present": false,
          "matched_amount_matches": false,
          "matched_payment_method": "",
          "match_confidence": null,
          "match_reason": ""
        },
        {
          "intent_id": "77fdeaf4-fe74-4434-a785-3c5b26c6abed",
          "captured_at": "2026-05-09T22:21:55.083Z",
          "received_at": "2026-05-09T22:21:56.690Z",
          "product_idx": "300",
          "product_price": 36000,
          "price_matches_order_amount": false,
          "client_id_present": true,
          "ga_session_id_present": true,
          "click_id_present": true,
          "click_id_hash_prefix": "1af66527003686e9",
          "match_status": "pending",
          "matched_order_no_present": false,
          "matched_amount_matches": false,
          "matched_payment_method": "",
          "match_confidence": null,
          "match_reason": ""
        },
        {
          "intent_id": "c70a1e17-2c5b-4f9b-98bf-79fdf4a9ce7c",
          "captured_at": "2026-05-09T21:46:26.658Z",
          "received_at": "2026-05-09T21:46:26.974Z",
          "product_idx": "317",
          "product_price": 59800,
          "price_matches_order_amount": false,
          "client_id_present": true,
          "ga_session_id_present": true,
          "click_id_present": true,
          "click_id_hash_prefix": "50ae537f74eda14b",
          "match_status": "pending",
          "matched_order_no_present": false,
          "matched_amount_matches": false,
          "matched_payment_method": "",
          "match_confidence": null,
          "match_reason": ""
        },
        {
          "intent_id": "5ab7c649-ed21-453c-91f8-29cfd954215a",
          "captured_at": "2026-05-09T21:38:51.432Z",
          "received_at": "2026-05-09T21:38:52.192Z",
          "product_idx": "198",
          "product_price": 35000,
          "price_matches_order_amount": false,
          "client_id_present": true,
          "ga_session_id_present": true,
          "click_id_present": true,
          "click_id_hash_prefix": "6ba417aa92ad3807",
          "match_status": "pending",
          "matched_order_no_present": false,
          "matched_amount_matches": false,
          "matched_payment_method": "",
          "match_confidence": null,
          "match_reason": ""
        }
      ],
      "verdict": "candidate_present"
    },
    {
      "order_no": "202605101857504",
      "channel_order_no": "2026051018061950",
      "payment_amount": 531000,
      "order_time": "2026-05-10T01:07:03.000Z",
      "lookback_hours": 24,
      "candidate_count": 50,
      "exact_price_click_candidate_count": 0,
      "top_candidates": [
        {
          "intent_id": "e2466c8f-81d5-462b-80d0-65fcbbffea07",
          "captured_at": "2026-05-10T00:11:05.173Z",
          "received_at": "2026-05-10T00:11:06.036Z",
          "product_idx": "317",
          "product_price": 59800,
          "price_matches_order_amount": false,
          "client_id_present": true,
          "ga_session_id_present": true,
          "click_id_present": true,
          "click_id_hash_prefix": "7636f77048d65511",
          "match_status": "pending",
          "matched_order_no_present": false,
          "matched_amount_matches": false,
          "matched_payment_method": "",
          "match_confidence": null,
          "match_reason": ""
        },
        {
          "intent_id": "cbe186bd-3100-433c-9e83-dcadc42126cd",
          "captured_at": "2026-05-09T23:41:17.905Z",
          "received_at": "2026-05-09T23:41:19.010Z",
          "product_idx": "317",
          "product_price": 59800,
          "price_matches_order_amount": false,
          "client_id_present": true,
          "ga_session_id_present": true,
          "click_id_present": true,
          "click_id_hash_prefix": "16dd5450371b3bb4",
          "match_status": "pending",
          "matched_order_no_present": false,
          "matched_amount_matches": false,
          "matched_payment_method": "",
          "match_confidence": null,
          "match_reason": ""
        },
        {
          "intent_id": "ec1de051-e4fb-41c9-8a9c-4d5b1c14b17e",
          "captured_at": "2026-05-09T23:22:36.509Z",
          "received_at": "2026-05-09T23:22:37.793Z",
          "product_idx": "173",
          "product_price": 36000,
          "price_matches_order_amount": false,
          "client_id_present": true,
          "ga_session_id_present": true,
          "click_id_present": false,
          "click_id_hash_prefix": "",
          "match_status": "pending",
          "matched_order_no_present": false,
          "matched_amount_matches": false,
          "matched_payment_method": "",
          "match_confidence": null,
          "match_reason": ""
        },
        {
          "intent_id": "1a1c7698-acd7-46df-a469-b95b75e4c7c7",
          "captured_at": "2026-05-09T22:38:40.419Z",
          "received_at": "2026-05-09T22:38:40.179Z",
          "product_idx": "198",
          "product_price": 35000,
          "price_matches_order_amount": false,
          "client_id_present": true,
          "ga_session_id_present": true,
          "click_id_present": true,
          "click_id_hash_prefix": "51b541e31be7e73a",
          "match_status": "pending",
          "matched_order_no_present": false,
          "matched_amount_matches": false,
          "matched_payment_method": "",
          "match_confidence": null,
          "match_reason": ""
        },
        {
          "intent_id": "9b6d57bf-7d3e-4ffc-8f98-7b3cbcb533b5",
          "captured_at": "2026-05-09T22:28:48.221Z",
          "received_at": "2026-05-09T22:28:48.460Z",
          "product_idx": "317",
          "product_price": 59800,
          "price_matches_order_amount": false,
          "client_id_present": true,
          "ga_session_id_present": true,
          "click_id_present": true,
          "click_id_hash_prefix": "278fc0a58a86bb27",
          "match_status": "pending",
          "matched_order_no_present": false,
          "matched_amount_matches": false,
          "matched_payment_method": "",
          "match_confidence": null,
          "match_reason": ""
        },
        {
          "intent_id": "77fdeaf4-fe74-4434-a785-3c5b26c6abed",
          "captured_at": "2026-05-09T22:21:55.083Z",
          "received_at": "2026-05-09T22:21:56.690Z",
          "product_idx": "300",
          "product_price": 36000,
          "price_matches_order_amount": false,
          "client_id_present": true,
          "ga_session_id_present": true,
          "click_id_present": true,
          "click_id_hash_prefix": "1af66527003686e9",
          "match_status": "pending",
          "matched_order_no_present": false,
          "matched_amount_matches": false,
          "matched_payment_method": "",
          "match_confidence": null,
          "match_reason": ""
        },
        {
          "intent_id": "c70a1e17-2c5b-4f9b-98bf-79fdf4a9ce7c",
          "captured_at": "2026-05-09T21:46:26.658Z",
          "received_at": "2026-05-09T21:46:26.974Z",
          "product_idx": "317",
          "product_price": 59800,
          "price_matches_order_amount": false,
          "client_id_present": true,
          "ga_session_id_present": true,
          "click_id_present": true,
          "click_id_hash_prefix": "50ae537f74eda14b",
          "match_status": "pending",
          "matched_order_no_present": false,
          "matched_amount_matches": false,
          "matched_payment_method": "",
          "match_confidence": null,
          "match_reason": ""
        },
        {
          "intent_id": "5ab7c649-ed21-453c-91f8-29cfd954215a",
          "captured_at": "2026-05-09T21:38:51.432Z",
          "received_at": "2026-05-09T21:38:52.192Z",
          "product_idx": "198",
          "product_price": 35000,
          "price_matches_order_amount": false,
          "client_id_present": true,
          "ga_session_id_present": true,
          "click_id_present": true,
          "click_id_hash_prefix": "6ba417aa92ad3807",
          "match_status": "pending",
          "matched_order_no_present": false,
          "matched_amount_matches": false,
          "matched_payment_method": "",
          "match_confidence": null,
          "match_reason": ""
        },
        {
          "intent_id": "70b1661e-1494-40e2-a493-8b0686928f06",
          "captured_at": "2026-05-09T21:30:07.990Z",
          "received_at": "2026-05-09T21:30:08.600Z",
          "product_idx": "198",
          "product_price": 35000,
          "price_matches_order_amount": false,
          "client_id_present": true,
          "ga_session_id_present": true,
          "click_id_present": true,
          "click_id_hash_prefix": "d28b46580d0a5fa4",
          "match_status": "pending",
          "matched_order_no_present": false,
          "matched_amount_matches": false,
          "matched_payment_method": "",
          "match_confidence": null,
          "match_reason": ""
        },
        {
          "intent_id": "77ad71a2-800e-4a93-b1f9-ed4b005d7a5f",
          "captured_at": "2026-05-09T21:22:16.049Z",
          "received_at": "2026-05-09T21:22:16.946Z",
          "product_idx": "300",
          "product_price": 36000,
          "price_matches_order_amount": false,
          "client_id_present": true,
          "ga_session_id_present": true,
          "click_id_present": true,
          "click_id_hash_prefix": "c91dbeb7b0fe48ef",
          "match_status": "pending",
          "matched_order_no_present": false,
          "matched_amount_matches": false,
          "matched_payment_method": "",
          "match_confidence": null,
          "match_reason": ""
        }
      ],
      "verdict": "ambiguous_or_missing"
    },
    {
      "order_no": "202605080592304",
      "channel_order_no": "2026050865473610",
      "payment_amount": 59800,
      "order_time": "2026-05-08T01:44:49.000Z",
      "lookback_hours": 24,
      "candidate_count": 50,
      "exact_price_click_candidate_count": 15,
      "top_candidates": [
        {
          "intent_id": "d0b00db6-288e-4820-86a4-29f83e7cc6da",
          "captured_at": "2026-05-08T01:10:54.296Z",
          "received_at": "2026-05-08T01:10:55.179Z",
          "product_idx": "317",
          "product_price": 59800,
          "price_matches_order_amount": true,
          "client_id_present": true,
          "ga_session_id_present": true,
          "click_id_present": true,
          "click_id_hash_prefix": "bf9e39b65301271d",
          "match_status": "pending",
          "matched_order_no_present": false,
          "matched_amount_matches": false,
          "matched_payment_method": "",
          "match_confidence": null,
          "match_reason": ""
        },
        {
          "intent_id": "a0ecc617-cb86-4f02-a1c3-1be2e52b7dd9",
          "captured_at": "2026-05-08T00:43:49.541Z",
          "received_at": "2026-05-08T00:43:50.493Z",
          "product_idx": "317",
          "product_price": 59800,
          "price_matches_order_amount": true,
          "client_id_present": true,
          "ga_session_id_present": true,
          "click_id_present": true,
          "click_id_hash_prefix": "c2c75966bbc675e0",
          "match_status": "pending",
          "matched_order_no_present": false,
          "matched_amount_matches": false,
          "matched_payment_method": "",
          "match_confidence": null,
          "match_reason": ""
        },
        {
          "intent_id": "a54bc263-e0eb-4de3-afb0-37ef31e44457",
          "captured_at": "2026-05-08T00:34:26.072Z",
          "received_at": "2026-05-08T00:34:26.932Z",
          "product_idx": "198",
          "product_price": 35000,
          "price_matches_order_amount": false,
          "client_id_present": true,
          "ga_session_id_present": true,
          "click_id_present": false,
          "click_id_hash_prefix": "",
          "match_status": "pending",
          "matched_order_no_present": false,
          "matched_amount_matches": false,
          "matched_payment_method": "",
          "match_confidence": null,
          "match_reason": ""
        },
        {
          "intent_id": "9753963e-c554-4bc5-b1f0-b09f96b32e43",
          "captured_at": "2026-05-08T00:19:44.043Z",
          "received_at": "2026-05-08T00:19:45.163Z",
          "product_idx": "225",
          "product_price": 68400,
          "price_matches_order_amount": false,
          "client_id_present": true,
          "ga_session_id_present": true,
          "click_id_present": true,
          "click_id_hash_prefix": "63ffa703d417bb27",
          "match_status": "pending",
          "matched_order_no_present": false,
          "matched_amount_matches": false,
          "matched_payment_method": "",
          "match_confidence": null,
          "match_reason": ""
        },
        {
          "intent_id": "b99a0728-90f5-4bfb-a717-87149f383392",
          "captured_at": "2026-05-08T00:06:33.510Z",
          "received_at": "2026-05-08T00:06:33.336Z",
          "product_idx": "317",
          "product_price": 59800,
          "price_matches_order_amount": true,
          "client_id_present": true,
          "ga_session_id_present": true,
          "click_id_present": true,
          "click_id_hash_prefix": "8cc3ec6fd925fa70",
          "match_status": "pending",
          "matched_order_no_present": false,
          "matched_amount_matches": false,
          "matched_payment_method": "",
          "match_confidence": null,
          "match_reason": ""
        },
        {
          "intent_id": "a09ee64e-be26-4d82-919b-3b8500d4b436",
          "captured_at": "2026-05-08T00:06:05.558Z",
          "received_at": "2026-05-08T00:06:06.413Z",
          "product_idx": "198",
          "product_price": 35000,
          "price_matches_order_amount": false,
          "client_id_present": true,
          "ga_session_id_present": true,
          "click_id_present": false,
          "click_id_hash_prefix": "",
          "match_status": "pending",
          "matched_order_no_present": false,
          "matched_amount_matches": false,
          "matched_payment_method": "",
          "match_confidence": null,
          "match_reason": ""
        },
        {
          "intent_id": "f8a89919-3e2d-4a2c-a1c3-80a4f8961184",
          "captured_at": "2026-05-07T23:54:41.270Z",
          "received_at": "2026-05-07T23:54:42.319Z",
          "product_idx": "386",
          "product_price": 36900,
          "price_matches_order_amount": false,
          "client_id_present": true,
          "ga_session_id_present": true,
          "click_id_present": true,
          "click_id_hash_prefix": "9edea960fbf5cde6",
          "match_status": "pending",
          "matched_order_no_present": false,
          "matched_amount_matches": false,
          "matched_payment_method": "",
          "match_confidence": null,
          "match_reason": ""
        },
        {
          "intent_id": "b595f54a-9d87-40c8-9b06-2171637cc348",
          "captured_at": "2026-05-07T23:51:24.329Z",
          "received_at": "2026-05-07T23:51:24.926Z",
          "product_idx": "300",
          "product_price": 36000,
          "price_matches_order_amount": false,
          "client_id_present": true,
          "ga_session_id_present": true,
          "click_id_present": true,
          "click_id_hash_prefix": "e169a8e6548d3ace",
          "match_status": "pending",
          "matched_order_no_present": false,
          "matched_amount_matches": false,
          "matched_payment_method": "",
          "match_confidence": null,
          "match_reason": ""
        },
        {
          "intent_id": "9311f967-9e42-40c5-9b3d-fc85314b83e1",
          "captured_at": "2026-05-07T23:30:38.842Z",
          "received_at": "2026-05-07T23:30:39.483Z",
          "product_idx": "317",
          "product_price": 59800,
          "price_matches_order_amount": true,
          "client_id_present": true,
          "ga_session_id_present": true,
          "click_id_present": true,
          "click_id_hash_prefix": "2794b74cb361a616",
          "match_status": "pending",
          "matched_order_no_present": false,
          "matched_amount_matches": false,
          "matched_payment_method": "",
          "match_confidence": null,
          "match_reason": ""
        },
        {
          "intent_id": "7f989b55-ad09-4db0-beb3-822879fb7dc8",
          "captured_at": "2026-05-07T22:59:25.747Z",
          "received_at": "2026-05-07T22:59:26.244Z",
          "product_idx": "317",
          "product_price": 59800,
          "price_matches_order_amount": true,
          "client_id_present": true,
          "ga_session_id_present": true,
          "click_id_present": true,
          "click_id_hash_prefix": "491c7ce3ae331de0",
          "match_status": "pending",
          "matched_order_no_present": false,
          "matched_amount_matches": false,
          "matched_payment_method": "",
          "match_confidence": null,
          "match_reason": ""
        }
      ],
      "verdict": "candidate_present"
    }
  ],
  "send_candidate": false,
  "actual_send_candidate": false
}
