{
  "ok": true,
  "checked_at_kst": "2026-05-24 11:50 KST",
  "mode": "green_read_only_page_long_threshold_fit_dry_run",
  "source_window_freshness_confidence": {
    "source": "VM Cloud SQLite hashed in VM process + GA4 BigQuery SHA256 session hash",
    "window": "rolling latest 7d",
    "freshness": "queried at runtime",
    "confidence": "medium_high for direction; medium for small source buckets"
  },
  "current_config": {
    "biocom_page_view_long_timer_seconds": 420,
    "thecleancoffee_page_view_long_timer_seconds": "needs_gtm_ui_confirmation",
    "interpretation": "현재 7분은 오래 읽은 방문을 보는 강한 기준이다. 기본 선행지표로 쓸지는 결제자/비결제자 체류시간 차이로 판단한다."
  },
  "threshold_candidates_seconds": [
    60,
    120,
    180,
    240,
    300,
    360,
    420,
    600
  ],
  "threshold_fit": [
    {
      "site": "biocom",
      "site_label": "바이오컴",
      "source_group": "meta",
      "source_label": "Meta 광고",
      "vm_safe_sessions": 204,
      "confirmed_vm_sessions": 131,
      "dropped_vm_sessions": 73,
      "ga4_joined_sessions": 194,
      "confirmed_ga4_joined_sessions": 125,
      "dropped_ga4_joined_sessions": 69,
      "join_rate_pct": 95.1,
      "confirmed_p50_seconds": 193.87,
      "dropped_p50_seconds": 124.27,
      "confirmed_p75_seconds": 343.46,
      "dropped_p75_seconds": 277.95,
      "ga4_page_view_long_event_rate_confirmed_pct": 19.2,
      "ga4_page_view_long_event_rate_dropped_pct": 17.39,
      "current_7min": {
        "seconds": 420,
        "label": "7분",
        "confirmed_above_sessions": 23,
        "dropped_above_sessions": 4,
        "confirmed_rate_pct": 18.4,
        "dropped_rate_pct": 5.8,
        "lift_pct": 12.6,
        "confirmed_coverage_pct": 18.4,
        "dropped_noise_pct": 5.8,
        "precision_proxy_pct": 85.19
      },
      "recommended_threshold_seconds": 120,
      "recommended_threshold_label": "2분",
      "recommendation_status": "seven_minutes_too_strict_for_primary_indicator",
      "threshold_rows": [
        {
          "seconds": 60,
          "label": "1분",
          "confirmed_above_sessions": 110,
          "dropped_above_sessions": 45,
          "confirmed_rate_pct": 88,
          "dropped_rate_pct": 65.22,
          "lift_pct": 22.78,
          "confirmed_coverage_pct": 88,
          "dropped_noise_pct": 65.22,
          "precision_proxy_pct": 70.97
        },
        {
          "seconds": 120,
          "label": "2분",
          "confirmed_above_sessions": 95,
          "dropped_above_sessions": 36,
          "confirmed_rate_pct": 76,
          "dropped_rate_pct": 52.17,
          "lift_pct": 23.83,
          "confirmed_coverage_pct": 76,
          "dropped_noise_pct": 52.17,
          "precision_proxy_pct": 72.52
        },
        {
          "seconds": 180,
          "label": "3분",
          "confirmed_above_sessions": 68,
          "dropped_above_sessions": 23,
          "confirmed_rate_pct": 54.4,
          "dropped_rate_pct": 33.33,
          "lift_pct": 21.07,
          "confirmed_coverage_pct": 54.4,
          "dropped_noise_pct": 33.33,
          "precision_proxy_pct": 74.73
        },
        {
          "seconds": 240,
          "label": "4분",
          "confirmed_above_sessions": 51,
          "dropped_above_sessions": 19,
          "confirmed_rate_pct": 40.8,
          "dropped_rate_pct": 27.54,
          "lift_pct": 13.26,
          "confirmed_coverage_pct": 40.8,
          "dropped_noise_pct": 27.54,
          "precision_proxy_pct": 72.86
        },
        {
          "seconds": 300,
          "label": "5분",
          "confirmed_above_sessions": 36,
          "dropped_above_sessions": 14,
          "confirmed_rate_pct": 28.8,
          "dropped_rate_pct": 20.29,
          "lift_pct": 8.51,
          "confirmed_coverage_pct": 28.8,
          "dropped_noise_pct": 20.29,
          "precision_proxy_pct": 72
        },
        {
          "seconds": 360,
          "label": "6분",
          "confirmed_above_sessions": 27,
          "dropped_above_sessions": 9,
          "confirmed_rate_pct": 21.6,
          "dropped_rate_pct": 13.04,
          "lift_pct": 8.56,
          "confirmed_coverage_pct": 21.6,
          "dropped_noise_pct": 13.04,
          "precision_proxy_pct": 75
        },
        {
          "seconds": 420,
          "label": "7분",
          "confirmed_above_sessions": 23,
          "dropped_above_sessions": 4,
          "confirmed_rate_pct": 18.4,
          "dropped_rate_pct": 5.8,
          "lift_pct": 12.6,
          "confirmed_coverage_pct": 18.4,
          "dropped_noise_pct": 5.8,
          "precision_proxy_pct": 85.19
        },
        {
          "seconds": 600,
          "label": "10분",
          "confirmed_above_sessions": 10,
          "dropped_above_sessions": 2,
          "confirmed_rate_pct": 8,
          "dropped_rate_pct": 2.9,
          "lift_pct": 5.1,
          "confirmed_coverage_pct": 8,
          "dropped_noise_pct": 2.9,
          "precision_proxy_pct": 83.33
        }
      ],
      "interpretation": "7분은 너무 강한 기준이다. 초고의도 segment로는 유지하되 기본 선행지표는 더 짧은 기준을 써야 한다."
    },
    {
      "site": "biocom",
      "site_label": "바이오컴",
      "source_group": "google_paid",
      "source_label": "Google 유료",
      "vm_safe_sessions": 9,
      "confirmed_vm_sessions": 2,
      "dropped_vm_sessions": 7,
      "ga4_joined_sessions": 9,
      "confirmed_ga4_joined_sessions": 2,
      "dropped_ga4_joined_sessions": 7,
      "join_rate_pct": 100,
      "confirmed_p50_seconds": 216.41,
      "dropped_p50_seconds": 36.84,
      "confirmed_p75_seconds": 216.41,
      "dropped_p75_seconds": 42.61,
      "ga4_page_view_long_event_rate_confirmed_pct": 50,
      "ga4_page_view_long_event_rate_dropped_pct": 71.43,
      "current_7min": {
        "seconds": 420,
        "label": "7분",
        "confirmed_above_sessions": 1,
        "dropped_above_sessions": 0,
        "confirmed_rate_pct": 50,
        "dropped_rate_pct": 0,
        "lift_pct": 50,
        "confirmed_coverage_pct": 50,
        "dropped_noise_pct": 0,
        "precision_proxy_pct": 100
      },
      "recommended_threshold_seconds": 60,
      "recommended_threshold_label": "1분",
      "recommendation_status": "insufficient_sample",
      "threshold_rows": [
        {
          "seconds": 60,
          "label": "1분",
          "confirmed_above_sessions": 2,
          "dropped_above_sessions": 1,
          "confirmed_rate_pct": 100,
          "dropped_rate_pct": 14.29,
          "lift_pct": 85.71,
          "confirmed_coverage_pct": 100,
          "dropped_noise_pct": 14.29,
          "precision_proxy_pct": 66.67
        },
        {
          "seconds": 120,
          "label": "2분",
          "confirmed_above_sessions": 2,
          "dropped_above_sessions": 1,
          "confirmed_rate_pct": 100,
          "dropped_rate_pct": 14.29,
          "lift_pct": 85.71,
          "confirmed_coverage_pct": 100,
          "dropped_noise_pct": 14.29,
          "precision_proxy_pct": 66.67
        },
        {
          "seconds": 180,
          "label": "3분",
          "confirmed_above_sessions": 2,
          "dropped_above_sessions": 1,
          "confirmed_rate_pct": 100,
          "dropped_rate_pct": 14.29,
          "lift_pct": 85.71,
          "confirmed_coverage_pct": 100,
          "dropped_noise_pct": 14.29,
          "precision_proxy_pct": 66.67
        },
        {
          "seconds": 240,
          "label": "4분",
          "confirmed_above_sessions": 1,
          "dropped_above_sessions": 1,
          "confirmed_rate_pct": 50,
          "dropped_rate_pct": 14.29,
          "lift_pct": 35.71,
          "confirmed_coverage_pct": 50,
          "dropped_noise_pct": 14.29,
          "precision_proxy_pct": 50
        },
        {
          "seconds": 300,
          "label": "5분",
          "confirmed_above_sessions": 1,
          "dropped_above_sessions": 1,
          "confirmed_rate_pct": 50,
          "dropped_rate_pct": 14.29,
          "lift_pct": 35.71,
          "confirmed_coverage_pct": 50,
          "dropped_noise_pct": 14.29,
          "precision_proxy_pct": 50
        },
        {
          "seconds": 360,
          "label": "6분",
          "confirmed_above_sessions": 1,
          "dropped_above_sessions": 0,
          "confirmed_rate_pct": 50,
          "dropped_rate_pct": 0,
          "lift_pct": 50,
          "confirmed_coverage_pct": 50,
          "dropped_noise_pct": 0,
          "precision_proxy_pct": 100
        },
        {
          "seconds": 420,
          "label": "7분",
          "confirmed_above_sessions": 1,
          "dropped_above_sessions": 0,
          "confirmed_rate_pct": 50,
          "dropped_rate_pct": 0,
          "lift_pct": 50,
          "confirmed_coverage_pct": 50,
          "dropped_noise_pct": 0,
          "precision_proxy_pct": 100
        },
        {
          "seconds": 600,
          "label": "10분",
          "confirmed_above_sessions": 1,
          "dropped_above_sessions": 0,
          "confirmed_rate_pct": 50,
          "dropped_rate_pct": 0,
          "lift_pct": 50,
          "confirmed_coverage_pct": 50,
          "dropped_noise_pct": 0,
          "precision_proxy_pct": 100
        }
      ],
      "interpretation": "표본이 작아 이 채널만으로 기준 시간을 확정하지 않는다."
    },
    {
      "site": "biocom",
      "site_label": "바이오컴",
      "source_group": "youtube",
      "source_label": "YouTube",
      "vm_safe_sessions": 12,
      "confirmed_vm_sessions": 5,
      "dropped_vm_sessions": 7,
      "ga4_joined_sessions": 11,
      "confirmed_ga4_joined_sessions": 5,
      "dropped_ga4_joined_sessions": 6,
      "join_rate_pct": 91.67,
      "confirmed_p50_seconds": 778.26,
      "dropped_p50_seconds": 404.94,
      "confirmed_p75_seconds": 780.76,
      "dropped_p75_seconds": 509.91,
      "ga4_page_view_long_event_rate_confirmed_pct": 0,
      "ga4_page_view_long_event_rate_dropped_pct": 50,
      "current_7min": {
        "seconds": 420,
        "label": "7분",
        "confirmed_above_sessions": 4,
        "dropped_above_sessions": 3,
        "confirmed_rate_pct": 80,
        "dropped_rate_pct": 50,
        "lift_pct": 30,
        "confirmed_coverage_pct": 80,
        "dropped_noise_pct": 50,
        "precision_proxy_pct": 57.14
      },
      "recommended_threshold_seconds": 420,
      "recommended_threshold_label": "7분",
      "recommendation_status": "seven_minutes_usable_as_high_intent_indicator",
      "threshold_rows": [
        {
          "seconds": 60,
          "label": "1분",
          "confirmed_above_sessions": 5,
          "dropped_above_sessions": 5,
          "confirmed_rate_pct": 100,
          "dropped_rate_pct": 83.33,
          "lift_pct": 16.67,
          "confirmed_coverage_pct": 100,
          "dropped_noise_pct": 83.33,
          "precision_proxy_pct": 50
        },
        {
          "seconds": 120,
          "label": "2분",
          "confirmed_above_sessions": 5,
          "dropped_above_sessions": 5,
          "confirmed_rate_pct": 100,
          "dropped_rate_pct": 83.33,
          "lift_pct": 16.67,
          "confirmed_coverage_pct": 100,
          "dropped_noise_pct": 83.33,
          "precision_proxy_pct": 50
        },
        {
          "seconds": 180,
          "label": "3분",
          "confirmed_above_sessions": 5,
          "dropped_above_sessions": 5,
          "confirmed_rate_pct": 100,
          "dropped_rate_pct": 83.33,
          "lift_pct": 16.67,
          "confirmed_coverage_pct": 100,
          "dropped_noise_pct": 83.33,
          "precision_proxy_pct": 50
        },
        {
          "seconds": 240,
          "label": "4분",
          "confirmed_above_sessions": 5,
          "dropped_above_sessions": 5,
          "confirmed_rate_pct": 100,
          "dropped_rate_pct": 83.33,
          "lift_pct": 16.67,
          "confirmed_coverage_pct": 100,
          "dropped_noise_pct": 83.33,
          "precision_proxy_pct": 50
        },
        {
          "seconds": 300,
          "label": "5분",
          "confirmed_above_sessions": 4,
          "dropped_above_sessions": 4,
          "confirmed_rate_pct": 80,
          "dropped_rate_pct": 66.67,
          "lift_pct": 13.33,
          "confirmed_coverage_pct": 80,
          "dropped_noise_pct": 66.67,
          "precision_proxy_pct": 50
        },
        {
          "seconds": 360,
          "label": "6분",
          "confirmed_above_sessions": 4,
          "dropped_above_sessions": 4,
          "confirmed_rate_pct": 80,
          "dropped_rate_pct": 66.67,
          "lift_pct": 13.33,
          "confirmed_coverage_pct": 80,
          "dropped_noise_pct": 66.67,
          "precision_proxy_pct": 50
        },
        {
          "seconds": 420,
          "label": "7분",
          "confirmed_above_sessions": 4,
          "dropped_above_sessions": 3,
          "confirmed_rate_pct": 80,
          "dropped_rate_pct": 50,
          "lift_pct": 30,
          "confirmed_coverage_pct": 80,
          "dropped_noise_pct": 50,
          "precision_proxy_pct": 57.14
        },
        {
          "seconds": 600,
          "label": "10분",
          "confirmed_above_sessions": 3,
          "dropped_above_sessions": 2,
          "confirmed_rate_pct": 60,
          "dropped_rate_pct": 33.33,
          "lift_pct": 26.67,
          "confirmed_coverage_pct": 60,
          "dropped_noise_pct": 33.33,
          "precision_proxy_pct": 60
        }
      ],
      "interpretation": "7분은 구매자 쪽 비중과 차이가 충분해 high-intent 지표로 쓸 수 있다."
    },
    {
      "site": "thecleancoffee",
      "site_label": "더클린커피",
      "source_group": "meta",
      "source_label": "Meta 광고",
      "vm_safe_sessions": 88,
      "confirmed_vm_sessions": 39,
      "dropped_vm_sessions": 49,
      "ga4_joined_sessions": 86,
      "confirmed_ga4_joined_sessions": 39,
      "dropped_ga4_joined_sessions": 47,
      "join_rate_pct": 97.73,
      "confirmed_p50_seconds": 188.81,
      "dropped_p50_seconds": 225.43,
      "confirmed_p75_seconds": 374.88,
      "dropped_p75_seconds": 335.28,
      "ga4_page_view_long_event_rate_confirmed_pct": 12.82,
      "ga4_page_view_long_event_rate_dropped_pct": 10.64,
      "current_7min": {
        "seconds": 420,
        "label": "7분",
        "confirmed_above_sessions": 8,
        "dropped_above_sessions": 5,
        "confirmed_rate_pct": 20.51,
        "dropped_rate_pct": 10.64,
        "lift_pct": 9.87,
        "confirmed_coverage_pct": 20.51,
        "dropped_noise_pct": 10.64,
        "precision_proxy_pct": 61.54
      },
      "recommended_threshold_seconds": 120,
      "recommended_threshold_label": "2분",
      "recommendation_status": "seven_minutes_too_strict_for_primary_indicator",
      "threshold_rows": [
        {
          "seconds": 60,
          "label": "1분",
          "confirmed_above_sessions": 35,
          "dropped_above_sessions": 42,
          "confirmed_rate_pct": 89.74,
          "dropped_rate_pct": 89.36,
          "lift_pct": 0.38,
          "confirmed_coverage_pct": 89.74,
          "dropped_noise_pct": 89.36,
          "precision_proxy_pct": 45.45
        },
        {
          "seconds": 120,
          "label": "2분",
          "confirmed_above_sessions": 29,
          "dropped_above_sessions": 29,
          "confirmed_rate_pct": 74.36,
          "dropped_rate_pct": 61.7,
          "lift_pct": 12.66,
          "confirmed_coverage_pct": 74.36,
          "dropped_noise_pct": 61.7,
          "precision_proxy_pct": 50
        },
        {
          "seconds": 180,
          "label": "3분",
          "confirmed_above_sessions": 23,
          "dropped_above_sessions": 27,
          "confirmed_rate_pct": 58.97,
          "dropped_rate_pct": 57.45,
          "lift_pct": 1.52,
          "confirmed_coverage_pct": 58.97,
          "dropped_noise_pct": 57.45,
          "precision_proxy_pct": 46
        },
        {
          "seconds": 240,
          "label": "4분",
          "confirmed_above_sessions": 17,
          "dropped_above_sessions": 20,
          "confirmed_rate_pct": 43.59,
          "dropped_rate_pct": 42.55,
          "lift_pct": 1.04,
          "confirmed_coverage_pct": 43.59,
          "dropped_noise_pct": 42.55,
          "precision_proxy_pct": 45.95
        },
        {
          "seconds": 300,
          "label": "5분",
          "confirmed_above_sessions": 14,
          "dropped_above_sessions": 14,
          "confirmed_rate_pct": 35.9,
          "dropped_rate_pct": 29.79,
          "lift_pct": 6.11,
          "confirmed_coverage_pct": 35.9,
          "dropped_noise_pct": 29.79,
          "precision_proxy_pct": 50
        },
        {
          "seconds": 360,
          "label": "6분",
          "confirmed_above_sessions": 12,
          "dropped_above_sessions": 9,
          "confirmed_rate_pct": 30.77,
          "dropped_rate_pct": 19.15,
          "lift_pct": 11.62,
          "confirmed_coverage_pct": 30.77,
          "dropped_noise_pct": 19.15,
          "precision_proxy_pct": 57.14
        },
        {
          "seconds": 420,
          "label": "7분",
          "confirmed_above_sessions": 8,
          "dropped_above_sessions": 5,
          "confirmed_rate_pct": 20.51,
          "dropped_rate_pct": 10.64,
          "lift_pct": 9.87,
          "confirmed_coverage_pct": 20.51,
          "dropped_noise_pct": 10.64,
          "precision_proxy_pct": 61.54
        },
        {
          "seconds": 600,
          "label": "10분",
          "confirmed_above_sessions": 5,
          "dropped_above_sessions": 3,
          "confirmed_rate_pct": 12.82,
          "dropped_rate_pct": 6.38,
          "lift_pct": 6.44,
          "confirmed_coverage_pct": 12.82,
          "dropped_noise_pct": 6.38,
          "precision_proxy_pct": 62.5
        }
      ],
      "interpretation": "7분은 너무 강한 기준이다. 초고의도 segment로는 유지하되 기본 선행지표는 더 짧은 기준을 써야 한다."
    },
    {
      "site": "thecleancoffee",
      "site_label": "더클린커피",
      "source_group": "google_paid",
      "source_label": "Google 유료",
      "vm_safe_sessions": 3,
      "confirmed_vm_sessions": 0,
      "dropped_vm_sessions": 3,
      "ga4_joined_sessions": 3,
      "confirmed_ga4_joined_sessions": 0,
      "dropped_ga4_joined_sessions": 3,
      "join_rate_pct": 100,
      "confirmed_p50_seconds": null,
      "dropped_p50_seconds": 43.09,
      "confirmed_p75_seconds": null,
      "dropped_p75_seconds": 43.09,
      "ga4_page_view_long_event_rate_confirmed_pct": null,
      "ga4_page_view_long_event_rate_dropped_pct": 100,
      "current_7min": {
        "seconds": 420,
        "label": "7분",
        "confirmed_above_sessions": 0,
        "dropped_above_sessions": 0,
        "confirmed_rate_pct": null,
        "dropped_rate_pct": 0,
        "lift_pct": null,
        "confirmed_coverage_pct": null,
        "dropped_noise_pct": 0,
        "precision_proxy_pct": null
      },
      "recommended_threshold_seconds": null,
      "recommended_threshold_label": null,
      "recommendation_status": "insufficient_sample",
      "threshold_rows": [
        {
          "seconds": 60,
          "label": "1분",
          "confirmed_above_sessions": 0,
          "dropped_above_sessions": 1,
          "confirmed_rate_pct": null,
          "dropped_rate_pct": 33.33,
          "lift_pct": null,
          "confirmed_coverage_pct": null,
          "dropped_noise_pct": 33.33,
          "precision_proxy_pct": 0
        },
        {
          "seconds": 120,
          "label": "2분",
          "confirmed_above_sessions": 0,
          "dropped_above_sessions": 0,
          "confirmed_rate_pct": null,
          "dropped_rate_pct": 0,
          "lift_pct": null,
          "confirmed_coverage_pct": null,
          "dropped_noise_pct": 0,
          "precision_proxy_pct": null
        },
        {
          "seconds": 180,
          "label": "3분",
          "confirmed_above_sessions": 0,
          "dropped_above_sessions": 0,
          "confirmed_rate_pct": null,
          "dropped_rate_pct": 0,
          "lift_pct": null,
          "confirmed_coverage_pct": null,
          "dropped_noise_pct": 0,
          "precision_proxy_pct": null
        },
        {
          "seconds": 240,
          "label": "4분",
          "confirmed_above_sessions": 0,
          "dropped_above_sessions": 0,
          "confirmed_rate_pct": null,
          "dropped_rate_pct": 0,
          "lift_pct": null,
          "confirmed_coverage_pct": null,
          "dropped_noise_pct": 0,
          "precision_proxy_pct": null
        },
        {
          "seconds": 300,
          "label": "5분",
          "confirmed_above_sessions": 0,
          "dropped_above_sessions": 0,
          "confirmed_rate_pct": null,
          "dropped_rate_pct": 0,
          "lift_pct": null,
          "confirmed_coverage_pct": null,
          "dropped_noise_pct": 0,
          "precision_proxy_pct": null
        },
        {
          "seconds": 360,
          "label": "6분",
          "confirmed_above_sessions": 0,
          "dropped_above_sessions": 0,
          "confirmed_rate_pct": null,
          "dropped_rate_pct": 0,
          "lift_pct": null,
          "confirmed_coverage_pct": null,
          "dropped_noise_pct": 0,
          "precision_proxy_pct": null
        },
        {
          "seconds": 420,
          "label": "7분",
          "confirmed_above_sessions": 0,
          "dropped_above_sessions": 0,
          "confirmed_rate_pct": null,
          "dropped_rate_pct": 0,
          "lift_pct": null,
          "confirmed_coverage_pct": null,
          "dropped_noise_pct": 0,
          "precision_proxy_pct": null
        },
        {
          "seconds": 600,
          "label": "10분",
          "confirmed_above_sessions": 0,
          "dropped_above_sessions": 0,
          "confirmed_rate_pct": null,
          "dropped_rate_pct": 0,
          "lift_pct": null,
          "confirmed_coverage_pct": null,
          "dropped_noise_pct": 0,
          "precision_proxy_pct": null
        }
      ],
      "interpretation": "표본이 작아 이 채널만으로 기준 시간을 확정하지 않는다."
    },
    {
      "site": "thecleancoffee",
      "site_label": "더클린커피",
      "source_group": "youtube",
      "source_label": "YouTube",
      "vm_safe_sessions": 24,
      "confirmed_vm_sessions": 14,
      "dropped_vm_sessions": 10,
      "ga4_joined_sessions": 24,
      "confirmed_ga4_joined_sessions": 14,
      "dropped_ga4_joined_sessions": 10,
      "join_rate_pct": 100,
      "confirmed_p50_seconds": 165.49,
      "dropped_p50_seconds": 175.15,
      "confirmed_p75_seconds": 220.84,
      "dropped_p75_seconds": 245.38,
      "ga4_page_view_long_event_rate_confirmed_pct": 0,
      "ga4_page_view_long_event_rate_dropped_pct": 10,
      "current_7min": {
        "seconds": 420,
        "label": "7분",
        "confirmed_above_sessions": 3,
        "dropped_above_sessions": 0,
        "confirmed_rate_pct": 21.43,
        "dropped_rate_pct": 0,
        "lift_pct": 21.43,
        "confirmed_coverage_pct": 21.43,
        "dropped_noise_pct": 0,
        "precision_proxy_pct": 100
      },
      "recommended_threshold_seconds": 360,
      "recommended_threshold_label": "6분",
      "recommendation_status": "seven_minutes_too_strict_for_primary_indicator",
      "threshold_rows": [
        {
          "seconds": 60,
          "label": "1분",
          "confirmed_above_sessions": 14,
          "dropped_above_sessions": 10,
          "confirmed_rate_pct": 100,
          "dropped_rate_pct": 100,
          "lift_pct": 0,
          "confirmed_coverage_pct": 100,
          "dropped_noise_pct": 100,
          "precision_proxy_pct": 58.33
        },
        {
          "seconds": 120,
          "label": "2분",
          "confirmed_above_sessions": 11,
          "dropped_above_sessions": 7,
          "confirmed_rate_pct": 78.57,
          "dropped_rate_pct": 70,
          "lift_pct": 8.57,
          "confirmed_coverage_pct": 78.57,
          "dropped_noise_pct": 70,
          "precision_proxy_pct": 61.11
        },
        {
          "seconds": 180,
          "label": "3분",
          "confirmed_above_sessions": 6,
          "dropped_above_sessions": 5,
          "confirmed_rate_pct": 42.86,
          "dropped_rate_pct": 50,
          "lift_pct": -7.14,
          "confirmed_coverage_pct": 42.86,
          "dropped_noise_pct": 50,
          "precision_proxy_pct": 54.55
        },
        {
          "seconds": 240,
          "label": "4분",
          "confirmed_above_sessions": 4,
          "dropped_above_sessions": 4,
          "confirmed_rate_pct": 28.57,
          "dropped_rate_pct": 40,
          "lift_pct": -11.43,
          "confirmed_coverage_pct": 28.57,
          "dropped_noise_pct": 40,
          "precision_proxy_pct": 50
        },
        {
          "seconds": 300,
          "label": "5분",
          "confirmed_above_sessions": 3,
          "dropped_above_sessions": 2,
          "confirmed_rate_pct": 21.43,
          "dropped_rate_pct": 20,
          "lift_pct": 1.43,
          "confirmed_coverage_pct": 21.43,
          "dropped_noise_pct": 20,
          "precision_proxy_pct": 60
        },
        {
          "seconds": 360,
          "label": "6분",
          "confirmed_above_sessions": 3,
          "dropped_above_sessions": 0,
          "confirmed_rate_pct": 21.43,
          "dropped_rate_pct": 0,
          "lift_pct": 21.43,
          "confirmed_coverage_pct": 21.43,
          "dropped_noise_pct": 0,
          "precision_proxy_pct": 100
        },
        {
          "seconds": 420,
          "label": "7분",
          "confirmed_above_sessions": 3,
          "dropped_above_sessions": 0,
          "confirmed_rate_pct": 21.43,
          "dropped_rate_pct": 0,
          "lift_pct": 21.43,
          "confirmed_coverage_pct": 21.43,
          "dropped_noise_pct": 0,
          "precision_proxy_pct": 100
        },
        {
          "seconds": 600,
          "label": "10분",
          "confirmed_above_sessions": 0,
          "dropped_above_sessions": 0,
          "confirmed_rate_pct": 0,
          "dropped_rate_pct": 0,
          "lift_pct": 0,
          "confirmed_coverage_pct": 0,
          "dropped_noise_pct": 0,
          "precision_proxy_pct": null
        }
      ],
      "interpretation": "7분은 너무 강한 기준이다. 초고의도 segment로는 유지하되 기본 선행지표는 더 짧은 기준을 써야 한다."
    }
  ],
  "safety": {
    "no_send": true,
    "no_write": true,
    "no_deploy": true,
    "no_publish": true,
    "raw_identifier_output": false
  }
}
